Workbook

Sheet README
A1: Tahoe 成本与预算模板
A3: 使用顺序
A4: 1. 先在 Parameters 填汇率、风险预留比例、默认固定成本。
A5: 2. 在 Unit_Costs 维护各模块单次成本与平均版本次数。
A6: 3. 在 Project_Estimator 按项目类型估算首版成本、试错成本、上架成本。
A7: 4. 在 Monthly_Budget 输入当月各类型项目数量，查看预算。
A8: 5. 在 Project_Ledger 逐项目登记实际发生额，月底复盘预算差异。
A10: 专业口径说明
A11: 直接成本：文本、图片、视频、搜索 API 调用费。
A12: 固定成本：服务器、数据库、SerpApi 月费、对象存储基础包等。
A13: 研发费用：开发、设计、测试、运维工时。
A14: 试错成本：改稿、重出图、重出视频、多轮 review 等返工成本。
... A26: 本模板已经预填 Tahoe 当前建议的质量优先模型分工，可直接修改。

Sheet Parameters
A1: 参数 | B1: 值 | C1: 说明
A2: USD_CNY_RATE | B2: 7.2 | C2: 美元兑人民币内部预算汇率
A3: RISK_BUFFER_RATE | B3: 0.15 | C3: 风险预留比例，建议 10%-20%
A4: GPT54_INPUT_PER_1M | B4: 2.5 | C4: OpenAI GPT-5.4 官方输入单价 / 1M tokens
A5: GPT54_OUTPUT_PER_1M | B5: 15 | C5: OpenAI GPT-5.4 官方输出单价 / 1M tokens
A6: GPT54MINI_PROXY_INPUT_PER_1M | B6: 0.25 | C6: gpt-5.4-mini 预算口径暂按 OpenAI 官方 GPT-5 mini 输入价代理估算
A7: GPT54MINI_PROXY_OUTPUT_PER_1M | B7: 2 | C7: gpt-5.4-mini 预算口径暂按 OpenAI 官方 GPT-5 mini 输出价代理估算
A8: GEMINI31PRO_INPUT_PER_1M | B8: 2 | C8: Gemini 3 Pro Preview <=200K prompt 输入单价
A9: GEMINI31PRO_OUTPUT_PER_1M | B9: 12 | C9: Gemini 3 Pro Preview <=200K prompt 输出单价
A10: QWEN3MAX_INPUT_PER_1M | B10: 1.2 | C10: Qwen3-Max <=32K 输入单价
A11: QWEN3MAX_OUTPUT_PER_1M | B11: 6 | C11: Qwen3-Max <=32K 输出单价
A12: QWEN35PLUS_INPUT_PER_1M | B12: 0.115 | C12: Qwen3.5-Plus <=128K 输入单价
A13: QWEN35PLUS_OUTPUT_PER_1M | B13: 0.688 | C13: Qwen3.5-Plus <=128K 输出单价
... A26: MONTHLY_QA_OPS_LABOR_USD | B26: 0 | C26: 测试 / 运维 / 设计人工成本

Sheet Unit_Costs
A1: 模块编码 | B1: 生产深度 | C1: 成本分类 | D1: 模块名称 | E1: 推荐模型 / 服务 | F1: 单次成本低值(USD) | G1: 单次成本高值(USD) | H1: 平均版本次数 | I1: 默认说明 | J1: 预算低值(USD) | K1: 预算高值(USD)
A2: SEARCH | B2: TEXT_ONLY | C2: 直接成本 | D2: 搜索 / 资料整理 | E2: Serper / SerpApi | F2: 0.001 | G2: 0.025 | H2: 1.2 | I2: 按单次查询计价；低值按 Serper， 高值按 SerpApi | J2: =F2*H2 | K2: =G2*H2
A3: TEXT_DRAFT | B3: TEXT_ONLY | C3: 直接成本 | D3: 文本首稿 | E3: Qwen3-Max / Gemini 3 Pro | F3: 0.054 | G3: 0.098 | H3: 1 | I3: 约按 25K 输入 + 4K 输出估算 | J3: =F3*H3 | K3: =G3*H3
A4: TEXT_REVISION | B4: TEXT_ONLY | C4: 试错成本 | D4: 文本改稿 | E4: Qwen3.5-Plus / GPT-5.4 | F4: 0.004 | G4: 0.09 | H4: 2 | I4: 低值按轻量平台改写，高值按旗舰重审重写 | J4: =F4*H4 | K4: =G4*H4
A5: TEXT_REVIEW | B5: TEXT_ONLY | C5: 试错成本 | D5: 质量 review | E5: GPT-5.4 | F5: 0.06 | G5: 0.138 | H5: 1.5 | I5: 约按 12K-25K 输入、2K-5K 输出估算 | J5: =F5*H5 | K5: =G5*H5
A6: PLATFORM_ADAPT | B6: TEXT_ONLY | C6: 上架成本 | D6: 平台适配 | E6: Qwen3.5-Plus / Qwen3-Max | F6: 0.003 | G6: 0.026 | H6: 1.5 | I6: 小红书 / 抖音等派生改写 | J6: =F6*H6 | K6: =G6*H6
A7: SCRIPT_DRAFT | B7: TEXT_STORYBOARD | C7: 直接成本 | D7: 脚本生成 | E7: Gemini 3 Pro Preview | F7: 0.196 | G7: 0.48 | H7: 1.5 | I7: 约按 50K-120K 输入、8K-20K 输出估算 | J7: =F7*H7 | K7: =G7*H7
A8: SCRIPT_REVISION | B8: TEXT_STORYBOARD | C8: 试错成本 | D8: 脚本改稿 | E8: Gemini 3 Pro Preview | F8: 0.12 | G8: 0.284 | H8: 1.5 | I8: 结构性重写、补镜头、节奏调整 | J8: =F8*H8 | K8: =G8*H8
A9: STORYBOARD | B9: TEXT_STORYBOARD | C9: 直接成本 | D9: Storyboard 生成 | E9: Gemini 3 Pro Preview | F9: 0.308 | G9: 0.66 | H9: 1.5 | I9: 分镜与镜头描述生成 | J9: =F9*H9 | K9: =G9*H9
A10: SCENE_CLASSIFY | B10: TEXT_STORYBOARD | C10: 直接成本 | D10: Scene classification | E10: GPT-5.4 Mini(按 GPT-5 mini 代理) | F10: 0.006 | G10: 0.016 | H10: 1.3 | I10: 透明说明：官方定价页未单列 gpt-5.4-mini，预算暂按 GPT-5 mini 代理 | J10: =F10*H10 | K10: =G10*H10
A11: ASSET_ANALYSIS | B11: TEXT_STORYBOARD | C11: 直接成本 | D11: Asset analysis | E11: GPT-5.4 Mini(按 GPT-5 mini 代理) | F11: 0.009 | G11: 0.017 | H11: 1.3 | I11: 素材缺口、资产依赖分析 | J11: =F11*H11 | K11: =G11*H11
A12: REPORT_REVIEW | B12: TEXT_STORYBOARD | C12: 试错成本 | D12: 报告 / review | E12: GPT-5.4 | F12: 0.11 | G12: 0.22 | H12: 1.5 | I12: 总结、诊断、复盘 | J12: =F12*H12 | K12: =G12*H12
A13: IMAGE_GEN | B13: TEXT_IMAGE | C13: 直接成本 | D13: 文生图尝试 | E13: Gemini 3 Pro Image Preview | F13: 0.134 | G13: 0.24 | H13: 6 | I13: 低值按 1K/2K， 高值按 4K 单张图 | J13: =F13*H13 | K13: =G13*H13
... A19: FINAL_QA | B19: TEXT_IMAGE_VIDEO | C19: 上架成本 | D19: 上架检查 | E19: GPT-5.4 Mini / GPT-5.4 | F19: 0.006 | G19: 0.053 | H19: 1 | I19: 最终质检、平台检查 | J19: =F19*H19 | K19: =G19*H19

Sheet Project_Estimator
A1: Tahoe 单项目成本测算
A3: 项目类型 | B3: 模块编码 | C3: 模块名称 | D3: 成本分类 | E3: 预算低值(USD) | F3: 预算高值(USD)
A4: TEXT_ONLY | B4: SEARCH | C4: =IFERROR(VLOOKUP(B4,Unit_Costs!$A:$K,4,FALSE),"") | D4: =IFERROR(VLOOKUP(B4,Unit_Costs!$A:$K,3,FALSE),"") | E4: =IFERROR(VLOOKUP(B4,Unit_Costs!$A:$K,10,FALSE),0) | F4: =IFERROR(VLOOKUP(B4,Unit_Costs!$A:$K,11,FALSE),0)
A5: TEXT_ONLY | B5: TEXT_DRAFT | C5: =IFERROR(VLOOKUP(B5,Unit_Costs!$A:$K,4,FALSE),"") | D5: =IFERROR(VLOOKUP(B5,Unit_Costs!$A:$K,3,FALSE),"") | E5: =IFERROR(VLOOKUP(B5,Unit_Costs!$A:$K,10,FALSE),0) | F5: =IFERROR(VLOOKUP(B5,Unit_Costs!$A:$K,11,FALSE),0)
A6: TEXT_ONLY | B6: TEXT_REVISION | C6: =IFERROR(VLOOKUP(B6,Unit_Costs!$A:$K,4,FALSE),"") | D6: =IFERROR(VLOOKUP(B6,Unit_Costs!$A:$K,3,FALSE),"") | E6: =IFERROR(VLOOKUP(B6,Unit_Costs!$A:$K,10,FALSE),0) | F6: =IFERROR(VLOOKUP(B6,Unit_Costs!$A:$K,11,FALSE),0)
A7: TEXT_ONLY | B7: TEXT_REVIEW | C7: =IFERROR(VLOOKUP(B7,Unit_Costs!$A:$K,4,FALSE),"") | D7: =IFERROR(VLOOKUP(B7,Unit_Costs!$A:$K,3,FALSE),"") | E7: =IFERROR(VLOOKUP(B7,Unit_Costs!$A:$K,10,FALSE),0) | F7: =IFERROR(VLOOKUP(B7,Unit_Costs!$A:$K,11,FALSE),0)
A8: TEXT_ONLY | B8: PLATFORM_ADAPT | C8: =IFERROR(VLOOKUP(B8,Unit_Costs!$A:$K,4,FALSE),"") | D8: =IFERROR(VLOOKUP(B8,Unit_Costs!$A:$K,3,FALSE),"") | E8: =IFERROR(VLOOKUP(B8,Unit_Costs!$A:$K,10,FALSE),0) | F8: =IFERROR(VLOOKUP(B8,Unit_Costs!$A:$K,11,FALSE),0)
A9: TEXT_STORYBOARD | B9: SEARCH | C9: =IFERROR(VLOOKUP(B9,Unit_Costs!$A:$K,4,FALSE),"") | D9: =IFERROR(VLOOKUP(B9,Unit_Costs!$A:$K,3,FALSE),"") | E9: =IFERROR(VLOOKUP(B9,Unit_Costs!$A:$K,10,FALSE),0) | F9: =IFERROR(VLOOKUP(B9,Unit_Costs!$A:$K,11,FALSE),0)
A10: TEXT_STORYBOARD | B10: SCRIPT_DRAFT | C10: =IFERROR(VLOOKUP(B10,Unit_Costs!$A:$K,4,FALSE),"") | D10: =IFERROR(VLOOKUP(B10,Unit_Costs!$A:$K,3,FALSE),"") | E10: =IFERROR(VLOOKUP(B10,Unit_Costs!$A:$K,10,FALSE),0) | F10: =IFERROR(VLOOKUP(B10,Unit_Costs!$A:$K,11,FALSE),0)
A11: TEXT_STORYBOARD | B11: SCRIPT_REVISION | C11: =IFERROR(VLOOKUP(B11,Unit_Costs!$A:$K,4,FALSE),"") | D11: =IFERROR(VLOOKUP(B11,Unit_Costs!$A:$K,3,FALSE),"") | E11: =IFERROR(VLOOKUP(B11,Unit_Costs!$A:$K,10,FALSE),0) | F11: =IFERROR(VLOOKUP(B11,Unit_Costs!$A:$K,11,FALSE),0)
A12: TEXT_STORYBOARD | B12: STORYBOARD | C12: =IFERROR(VLOOKUP(B12,Unit_Costs!$A:$K,4,FALSE),"") | D12: =IFERROR(VLOOKUP(B12,Unit_Costs!$A:$K,3,FALSE),"") | E12: =IFERROR(VLOOKUP(B12,Unit_Costs!$A:$K,10,FALSE),0) | F12: =IFERROR(VLOOKUP(B12,Unit_Costs!$A:$K,11,FALSE),0)
A13: TEXT_STORYBOARD | B13: SCENE_CLASSIFY | C13: =IFERROR(VLOOKUP(B13,Unit_Costs!$A:$K,4,FALSE),"") | D13: =IFERROR(VLOOKUP(B13,Unit_Costs!$A:$K,3,FALSE),"") | E13: =IFERROR(VLOOKUP(B13,Unit_Costs!$A:$K,10,FALSE),0) | F13: =IFERROR(VLOOKUP(B13,Unit_Costs!$A:$K,11,FALSE),0)
A14: TEXT_STORYBOARD | B14: ASSET_ANALYSIS | C14: =IFERROR(VLOOKUP(B14,Unit_Costs!$A:$K,4,FALSE),"") | D14: =IFERROR(VLOOKUP(B14,Unit_Costs!$A:$K,3,FALSE),"") | E14: =IFERROR(VLOOKUP(B14,Unit_Costs!$A:$K,10,FALSE),0) | F14: =IFERROR(VLOOKUP(B14,Unit_Costs!$A:$K,11,FALSE),0)
A15: TEXT_STORYBOARD | B15: REPORT_REVIEW | C15: =IFERROR(VLOOKUP(B15,Unit_Costs!$A:$K,4,FALSE),"") | D15: =IFERROR(VLOOKUP(B15,Unit_Costs!$A:$K,3,FALSE),"") | E15: =IFERROR(VLOOKUP(B15,Unit_Costs!$A:$K,10,FALSE),0) | F15: =IFERROR(VLOOKUP(B15,Unit_Costs!$A:$K,11,FALSE),0)
... A38: TEXT_IMAGE_VIDEO | B38: FINAL_QA | C38: =IFERROR(VLOOKUP(B38,Unit_Costs!$A:$K,4,FALSE),"") | D38: =IFERROR(VLOOKUP(B38,Unit_Costs!$A:$K,3,FALSE),"") | E38: =IFERROR(VLOOKUP(B38,Unit_Costs!$A:$K,10,FALSE),0) | F38: =IFERROR(VLOOKUP(B38,Unit_Costs!$A:$K,11,FALSE),0)
A41: 项目类型汇总 | B41: 预算低值(USD) | C41: 预算高值(USD)
A42: TEXT_ONLY | B42: =SUMIF($A$4:$A$38,A42,$E$4:$E$38) | C42: =SUMIF($A$4:$A$38,A42,$F$4:$F$38)
A43: TEXT_STORYBOARD | B43: =SUMIF($A$4:$A$38,A43,$E$4:$E$38) | C43: =SUMIF($A$4:$A$38,A43,$F$4:$F$38)
A44: TEXT_IMAGE | B44: =SUMIF($A$4:$A$38,A44,$E$4:$E$38) | C44: =SUMIF($A$4:$A$38,A44,$F$4:$F$38)
A45: TEXT_IMAGE_VIDEO | B45: =SUMIF($A$4:$A$38,A45,$E$4:$E$38) | C45: =SUMIF($A$4:$A$38,A45,$F$4:$F$38)

Sheet Monthly_Budget
A1: Tahoe 月预算
A3: 项目预算 | H3: 当前假设
A4: 项目类型 | B4: 月数量 | C4: 单项目预算低值(USD) | D4: 单项目预算高值(USD) | E4: 小计低值(USD) | F4: 小计高值(USD) | H4: 项目量假设：TEXT_ONLY 40 / TEXT_STORYBOARD 18 / TEXT_IMAGE 10 / TEXT_IMAGE_VIDEO 6
A5: TEXT_ONLY | B5: 40 | C5: =Project_Estimator!B41 | D5: =Project_Estimator!C41 | E5: =B5*C5 | F5: =B5*D5 | H5: 工具订阅已计入：ChatGPT Plus、Google AI Ultra(当前 $125/月)、See Dance 月摊
A6: TEXT_STORYBOARD | B6: 18 | C6: =Project_Estimator!B42 | D6: =Project_Estimator!C42 | E6: =B6*C6 | F6: =B6*D6 | H6: Google AI Ultra 从 2026-05 起若涨到 $250/月，请把 Parameters 的工具订阅改为 298.92 USD
A7: TEXT_IMAGE | B7: 10 | C7: =Project_Estimator!B43 | D7: =Project_Estimator!C43 | E7: =B7*C7 | F7: =B7*D7 | H7: 服务器 / 数据库成本为预算占位值，后续可替换为真实账单
A8: TEXT_IMAGE_VIDEO | B8: 6 | C8: =Project_Estimator!B44 | D8: =Project_Estimator!C44 | E8: =B8*C8 | F8: =B8*D8
A11: 固定成本预算
A12: 固定成本项 | B12: 月预算(USD) | C12: 说明
A13: 云服务器 | B13: =Parameters!B3 | C13: 服务器月固定成本
A14: 数据库 / 存储 / CDN | B14: =Parameters!B4 | C14: 数据库、存储、CDN
A15: SerpApi 固定月费 | B15: =Parameters!B5 | C15: 固定 API 套餐
A16: 其他固定技术成本 | B16: =Parameters!B6 | C16: 其他基础设施
A17: 工具订阅 | B17: =Parameters!B7 | C17: 若要纳入平台预算可填写
A18: 研发人工 | B18: =Parameters!B8 | C18: 开发成本
A19: 测试 / 运维 / 设计人工 | B19: =Parameters!B9 | C19: 运营与交付支持
A22: 预算汇总
A23: 项目直接成本低值 | B23: =SUM(E5:E8)
A24: 项目直接成本高值 | B24: =SUM(F5:F8)
A25: 固定成本合计 | B25: =SUM(B13:B19)
A26: 风险预留低值 | B26: =($B$23+$B$25)*Parameters!B2
A27: 风险预留高值 | B27: =($B$24+$B$25)*Parameters!B2
A28: 月总预算低值 | B28: =B23+B25+B26
A29: 月总预算高值 | B29: =B24+B25+B27
A30: 折人民币低值 | B30: =B28*Parameters!B1
A31: 折人民币高值 | B31: =B29*Parameters!B1

Sheet Project_Ledger
A1: 项目ID | B1: 项目名称 | C1: 业务线 | D1: 生产深度 | E1: 状态 | F1: 开始日期 | G1: 上架日期 | H1: 文本版本数 | I1: 图片尝试数 | J1: 视频尝试数 | K1: 搜索成本(USD) | L1: 文本成本(USD) | M1: 图片成本(USD) | N1: 视频成本(USD) | O1: Review成本(USD) | P1: 上架交付成本(USD) | Q1: 固定成本分摊(USD) | R1: 总成本(USD) | S1: 项目收入(USD) | T1: 毛利(USD) | U1: 备注
H2: 0 | I2: 0 | J2: 0 | K2: 0 | L2: 0 | M2: 0 | N2: 0 | O2: 0 | P2: 0 | Q2: 0 | R2: =SUM(K2:Q2) | S2: 0 | T2: =S2-R2
H3: 0 | I3: 0 | J3: 0 | K3: 0 | L3: 0 | M3: 0 | N3: 0 | O3: 0 | P3: 0 | Q3: 0 | R3: =SUM(K3:Q3) | S3: 0 | T3: =S3-R3
H4: 0 | I4: 0 | J4: 0 | K4: 0 | L4: 0 | M4: 0 | N4: 0 | O4: 0 | P4: 0 | Q4: 0 | R4: =SUM(K4:Q4) | S4: 0 | T4: =S4-R4
H5: 0 | I5: 0 | J5: 0 | K5: 0 | L5: 0 | M5: 0 | N5: 0 | O5: 0 | P5: 0 | Q5: 0 | R5: =SUM(K5:Q5) | S5: 0 | T5: =S5-R5
H6: 0 | I6: 0 | J6: 0 | K6: 0 | L6: 0 | M6: 0 | N6: 0 | O6: 0 | P6: 0 | Q6: 0 | R6: =SUM(K6:Q6) | S6: 0 | T6: =S6-R6
H7: 0 | I7: 0 | J7: 0 | K7: 0 | L7: 0 | M7: 0 | N7: 0 | O7: 0 | P7: 0 | Q7: 0 | R7: =SUM(K7:Q7) | S7: 0 | T7: =S7-R7
H8: 0 | I8: 0 | J8: 0 | K8: 0 | L8: 0 | M8: 0 | N8: 0 | O8: 0 | P8: 0 | Q8: 0 | R8: =SUM(K8:Q8) | S8: 0 | T8: =S8-R8
H9: 0 | I9: 0 | J9: 0 | K9: 0 | L9: 0 | M9: 0 | N9: 0 | O9: 0 | P9: 0 | Q9: 0 | R9: =SUM(K9:Q9) | S9: 0 | T9: =S9-R9
H10: 0 | I10: 0 | J10: 0 | K10: 0 | L10: 0 | M10: 0 | N10: 0 | O10: 0 | P10: 0 | Q10: 0 | R10: =SUM(K10:Q10) | S10: 0 | T10: =S10-R10
H11: 0 | I11: 0 | J11: 0 | K11: 0 | L11: 0 | M11: 0 | N11: 0 | O11: 0 | P11: 0 | Q11: 0 | R11: =SUM(K11:Q11) | S11: 0 | T11: =S11-R11
H12: 0 | I12: 0 | J12: 0 | K12: 0 | L12: 0 | M12: 0 | N12: 0 | O12: 0 | P12: 0 | Q12: 0 | R12: =SUM(K12:Q12) | S12: 0 | T12: =S12-R12
H13: 0 | I13: 0 | J13: 0 | K13: 0 | L13: 0 | M13: 0 | N13: 0 | O13: 0 | P13: 0 | Q13: 0 | R13: =SUM(K13:Q13) | S13: 0 | T13: =S13-R13
... H16: 0 | I16: 0 | J16: 0 | K16: 0 | L16: 0 | M16: 0 | N16: 0 | O16: 0 | P16: 0 | Q16: 0 | R16: =SUM(K16:Q16) | S16: 0 | T16: =S16-R16

Sheet Subscriptions
A1: 订阅项 | B1: 币种 | C1: 当前金额 | D1: 折月金额(USD) | E1: 计入口径 | F1: 备注
A2: ChatGPT Plus | B2: USD | C2: 20 | D2: 20 | E2: 工具订阅 | F2: 个人订阅；若平台统一使用可计入管理工具费
A3: Google AI Ultra | B3: USD | C3: 125 | D3: 125 | E3: 工具订阅 | F3: 当前 2026-03/04 促销价；2026-05 起预计 $250/月
A4: See Dance | B4: CNY | C4: 2499 | D4: 28.92 | E4: 工具订阅 | F4: 按年费 / 12 / 汇率 7.2 折算
A5: SerpApi | B5: USD | C5: 25 | D5: 25 | E5: 固定技术成本 | F5: 平台固定 API 套餐
A8: 说明
A9: 如果你想只看平台 API / 交付成本，可在 Monthly_Budget 里把工具订阅行清零。
A10: 如果你想看完整经营成本，则保留工具订阅、固定技术成本与人工。

Sheet Pricing_Sources
A1: 日期 | B1: 类别 | C1: 项目 | D1: 价格摘记 | E1: 来源 | F1: 备注
A2: 2026-03-24 | B2: OpenAI | C2: GPT-5.4 | D2: Input $2.50 / 1M, Output $15.00 / 1M | E2: https://openai.com/api/pricing/ | F2: 官方 API 定价页
A3: 2026-03-24 | B3: OpenAI | C3: GPT-5 mini | D3: Input $0.25 / 1M, Output $2.00 / 1M | E3: https://openai.com/api/pricing/ | F3: 用于 gpt-5.4-mini 预算代理口径
A4: 2026-03-24 | B4: Gemini | C4: Gemini 3 Pro Preview | D4: Input $2 / 1M, Output $12 / 1M (<=200K prompts) | E4: https://ai.google.dev/pricing | F4: 官方 Gemini Developer API 定价
A5: 2026-03-24 | B5: Gemini | C5: Gemini 3 Pro Image Preview | D5: 1K/2K image about $0.134 each; 4K about $0.24 each | E5: https://ai.google.dev/gemini-api/docs/pricing?hl=fr | F5: 官方定价页不同语言镜像，内容一致
A6: 2026-03-24 | B6: Gemini | C6: Veo 3.1 | D6: Fast $0.15/s, Standard $0.40/s | E6: https://ai.google.dev/pricing | F6: 官方 Gemini Developer API 定价
A7: 2026-03-24 | B7: Qwen | C7: qwen3-max | D7: Input $1.2 / 1M, Output $6 / 1M (<=32K) | E7: https://www.alibabacloud.com/help/en/model-studio/billing-for-model-studio | F7: 官方 Model Studio 文档
A8: 2026-03-24 | B8: Qwen | C8: qwen3.5-plus | D8: Input $0.115 / 1M, Output $0.688 / 1M (<=128K) | E8: https://www.alibabacloud.com/help/en/model-studio/getting-started/models | F8: 官方 Model Studio 文档
A9: 2026-03-24 | B9: Search | C9: Serper | D9: $50 / 50k credits = $0.001 per query | E9: https://serper.dev/ | F9: 官方站点 pricing
A10: 2026-03-24 | B10: Search | C10: SerpApi | D10: $25 / 1k searches = $0.025 per query | E10: https://serpapi.com/pricing | F10: 官方 pricing
